<annotation>
	<folder>images_dir</folder>
	<filename>Town03_015480.jpeg</filename>
	<path>/home/marco/carla_training/Carla-Object-Detection-Dataset/train/images_dir/Town03_015480.jpeg</path>
	<source>
		<database>Unknown</database>
	</source>
	<size>
		<width>640</width>
		<height>380</height>
		<depth>3</depth>
	</size>
	<segmented>0</segmented>
	<object>
		<name>vehicle</name>
		<pose>Unspecified</pose>
		<truncated>0</truncated>
		<difficult>0</difficult>
		<bndbox>
			<xmin>513</xmin>
			<ymin>202</ymin>
			<xmax>536</xmax>
			<ymax>214</ymax>
		</bndbox>
	</object>
	<object>
		<name>vehicle</name>
		<pose>Unspecified</pose>
		<truncated>0</truncated>
		<difficult>0</difficult>
		<bndbox>
			<xmin>340</xmin>
			<ymin>198</ymin>
			<xmax>416</xmax>
			<ymax>255</ymax>
		</bndbox>
	</object>
</annotation>
